LICENSE
MANIFEST.in
README.rst
setup.cfg
setup.py
memprof/__init__.py
memprof/__main__.py
memprof/getsize.pyx
memprof/memprof.py
memprof/mp_utils.py
memprof.egg-info/PKG-INFO
memprof.egg-info/SOURCES.txt
memprof.egg-info/dependency_links.txt
memprof.egg-info/not-zip-safe
memprof.egg-info/requires.txt
memprof.egg-info/top_level.txt
scripts/mp_plot