Metadata-Version: 1.1
Name: memprof
Version: 0.3.5
Summary: A memory profiler for Python. As easy as adding a decorator.
Home-page: http://jmdana.github.io/memprof/
Author: Jose M. Dana
Author-email: UNKNOWN
License: GNU General Public License v3 (GPLv3)
Keywords: memory usage profiler decorator variables charts plots graphical
Platform: UNKNOWN
Classifier: Development Status :: 5 - Production/Stable
Classifier: Topic :: Utilities
Classifier: Topic :: Software Development
Classifier: Programming Language :: Python
Classifier: Programming Language :: Python :: 2
Classifier: Programming Language :: Python :: 2.6
Classifier: Programming Language :: Python :: 2.7
Classifier: Programming Language :: Python :: 3
Classifier: Programming Language :: Python :: 3.1
Classifier: Programming Language :: Python :: 3.2
Classifier: Programming Language :: Python :: 3.3
Classifier: Operating System :: Unix
Classifier: Operating System :: MacOS
Classifier: Operating System :: POSIX
Classifier: Intended Audience :: Developers
Classifier: Intended Audience :: Information Technology
Classifier: Intended Audience :: Science/Research
Classifier: License :: OSI Approved :: GNU General Public License v3 (GPLv3)
Requires: argparse
Requires: matplotlib
Requires: cython
Provides: memprof
